odoo/addons/sale_timesheet_project_manual/README.rst
odoo/addons/sale_timesheet_project_manual/__init__.py
odoo/addons/sale_timesheet_project_manual/__manifest__.py
odoo/addons/sale_timesheet_project_manual/i18n/fr.po
odoo/addons/sale_timesheet_project_manual/i18n/pt_BR.po
odoo/addons/sale_timesheet_project_manual/i18n/sale_timesheet_project_manual.pot
odoo/addons/sale_timesheet_project_manual/models/__init__.py
odoo/addons/sale_timesheet_project_manual/models/sale_order.py
odoo/addons/sale_timesheet_project_manual/readme/CONTRIBUTORS.rst
odoo/addons/sale_timesheet_project_manual/readme/DESCRIPTION.rst
odoo/addons/sale_timesheet_project_manual/readme/USAGE.rst
odoo/addons/sale_timesheet_project_manual/static/description/icon.png
odoo/addons/sale_timesheet_project_manual/static/description/index.html
odoo/addons/sale_timesheet_project_manual/tests/__init__.py
odoo/addons/sale_timesheet_project_manual/tests/test_sale_timesheet_project_manual.py
odoo/addons/sale_timesheet_project_manual/views/sale_order.xml
odoo_addon_sale_timesheet_project_manual-16.0.1.0.0.5.dist-info/METADATA
odoo_addon_sale_timesheet_project_manual-16.0.1.0.0.5.dist-info/WHEEL
odoo_addon_sale_timesheet_project_manual-16.0.1.0.0.5.dist-info/top_level.txt
odoo_addon_sale_timesheet_project_manual-16.0.1.0.0.5.dist-info/RECORD
